main.py
pyapp_demo-0.1.0.dist-info/METADATA
pyapp_demo-0.1.0.dist-info/WHEEL
pyapp_demo-0.1.0.dist-info/top_level.txt
pyapp_demo-0.1.0.dist-info/RECORD
