Metadata-Version: 2.4
Name: pyapp-demo
Version: 0.1.0
Summary: Add your description here
Requires-Python: >=3.12
Requires-Dist: pandas>=2.3.1
Requires-Dist: pyapp>=4.16.1
